{
  "fileSystemType": "FAT32",
  "disk": {
    "id": "disk-1",
    "totalBlocks": 200,
    "blockSize": 4096,
    "fragmentRate": 15.5,
    "freeBlocks": [150, 151, 152, 153, 154, 155, 156, 157, 158, 159, 160, 161, 162, 163, 164, 165, 166, 167, 168, 169, 170, 171, 172, 173, 174, 175, 176, 177, 178, 179, 180, 181, 182, 183, 184, 185, 186, 187, 188, 189, 190, 191, 192, 193, 194, 195, 196, 197, 198, 199],
    "usedBlocks": {},
    "files": [
      {
        "id": "root",
        "name": ".",
        "type": "directory",
        "size": 0,
        "blocks": [],
        "parentId": "",
        "createTime": "2024-01-01T08:00:00.000Z",
        "allocationAlgorithm": null,
        "inode": 2,
        "deviceId": 1,
        "physicalPath": "/example/.",
        "extents": []
      },
      {
        "id": "file-1",
        "name": "continuous_file.txt",
        "type": "file",
        "size": 12288,
        "blocks": [10, 11, 12],
        "parentId": "root",
        "createTime": "2024-01-01T10:00:00.000Z",
        "allocationAlgorithm": "continuous",
        "inode": 1001,
        "deviceId": 1,
        "physicalPath": "/example/continuous_file.txt",
        "extents": [
          {
            "logicalOffset": 0,
            "physicalOffset": 40960,
            "length": 12288
          }
        ]
      },
      {
        "id": "file-2",
        "name": "linked_file.pdf",
        "type": "file",
        "size": 16384,
        "blocks": [20, 35, 48, 52],
        "parentId": "root",
        "createTime": "2024-01-01T11:00:00.000Z",
        "allocationAlgorithm": "linked",
        "inode": 1002,
        "deviceId": 1,
        "physicalPath": "/example/linked_file.pdf",
        "extents": [
          {
            "logicalOffset": 0,
            "physicalOffset": 81920,
            "length": 4096
          },
          {
            "logicalOffset": 4096,
            "physicalOffset": 143360,
            "length": 4096
          },
          {
            "logicalOffset": 8192,
            "physicalOffset": 196608,
            "length": 4096
          },
          {
            "logicalOffset": 12288,
            "physicalOffset": 212992,
            "length": 4096
          }
        ]
      },
      {
        "id": "file-3",
        "name": "indexed_file.dat",
        "type": "file",
        "size": 20480,
        "blocks": [100, 110, 115, 120, 125, 130],
        "parentId": "root",
        "createTime": "2024-01-01T12:00:00.000Z",
        "allocationAlgorithm": "indexed",
        "inode": 1003,
        "deviceId": 1,
        "physicalPath": "/example/indexed_file.dat",
        "extents": [
          {
            "logicalOffset": 0,
            "physicalOffset": 409600,
            "length": 4096
          },
          {
            "logicalOffset": 4096,
            "physicalOffset": 450560,
            "length": 4096
          },
          {
            "logicalOffset": 8192,
            "physicalOffset": 491520,
            "length": 4096
          },
          {
            "logicalOffset": 12288,
            "physicalOffset": 512000,
            "length": 4096
          },
          {
            "logicalOffset": 16384,
            "physicalOffset": 532480,
            "length": 4096
          }
        ]
      },
      {
        "id": "file-4",
        "name": "large_continuous.bin",
        "type": "file",
        "size": 32768,
        "blocks": [60, 61, 62, 63, 64, 65, 66, 67],
        "parentId": "root",
        "createTime": "2024-01-01T13:00:00.000Z",
        "allocationAlgorithm": "continuous",
        "inode": 1004,
        "deviceId": 1,
        "physicalPath": "/example/large_continuous.bin",
        "extents": [
          {
            "logicalOffset": 0,
            "physicalOffset": 245760,
            "length": 32768
          }
        ]
      },
      {
        "id": "file-5",
        "name": "fragmented_linked.log",
        "type": "file",
        "size": 8192,
        "blocks": [70, 85, 90],
        "parentId": "root",
        "createTime": "2024-01-01T14:00:00.000Z",
        "allocationAlgorithm": "linked",
        "inode": 1005,
        "deviceId": 1,
        "physicalPath": "/example/fragmented_linked.log",
        "extents": [
          {
            "logicalOffset": 0,
            "physicalOffset": 286720,
            "length": 4096
          },
          {
            "logicalOffset": 4096,
            "physicalOffset": 348160,
            "length": 4096
          }
        ]
      },
      {
        "id": "file-6",
        "name": "multi_indexed.img",
        "type": "file",
        "size": 24576,
        "blocks": [140, 145, 148, 150, 152, 155, 158],
        "parentId": "root",
        "createTime": "2024-01-01T15:00:00.000Z",
        "allocationAlgorithm": "indexed",
        "inode": 1006,
        "deviceId": 1,
        "physicalPath": "/example/multi_indexed.img",
        "extents": [
          {
            "logicalOffset": 0,
            "physicalOffset": 573440,
            "length": 4096
          },
          {
            "logicalOffset": 4096,
            "physicalOffset": 593920,
            "length": 4096
          },
          {
            "logicalOffset": 8192,
            "physicalOffset": 606208,
            "length": 4096
          },
          {
            "logicalOffset": 12288,
            "physicalOffset": 614400,
            "length": 4096
          },
          {
            "logicalOffset": 16384,
            "physicalOffset": 622592,
            "length": 4096
          },
          {
            "logicalOffset": 20480,
            "physicalOffset": 634880,
            "length": 4096
          }
        ]
      },
      {
        "id": "dir-1",
        "name": "documents",
        "type": "directory",
        "size": 0,
        "blocks": [],
        "parentId": "root",
        "createTime": "2024-01-01T16:00:00.000Z",
        "allocationAlgorithm": null,
        "inode": 2001,
        "deviceId": 1,
        "physicalPath": "/example/documents",
        "extents": []
      },
      {
        "id": "file-7",
        "name": "nested_continuous.txt",
        "type": "file",
        "size": 4096,
        "blocks": [5],
        "parentId": "dir-1",
        "createTime": "2024-01-01T17:00:00.000Z",
        "allocationAlgorithm": "continuous",
        "inode": 1007,
        "deviceId": 1,
        "physicalPath": "/example/documents/nested_continuous.txt",
        "extents": [
          {
            "logicalOffset": 0,
            "physicalOffset": 20480,
            "length": 4096
          }
        ]
      }
    ]
  }
}
